{
  "name": "napari-tomocube-data-viewer",
  "display_name": "Tomocube data viewer",
  "visibility": "public",
  "icon": "",
  "categories": [],
  "schema_version": "0.2.0",
  "on_activate": null,
  "on_deactivate": null,
  "contributions": {
    "commands": [
      {
        "id": "napari-tomocube-data-viewer.get_reader",
        "title": "Open data with Tomocube data viewer",
        "python_name": "napari_tomocube_data_viewer._reader:napari_get_reader",
        "short_title": null,
        "category": null,
        "icon": null,
        "enablement": null
      }
    ],
    "readers": [
      {
        "command": "napari-tomocube-data-viewer.get_reader",
        "filename_patterns": [
          "*.TCF"
        ],
        "accepts_directories": false
      }
    ],
    "writers": null,
    "widgets": null,
    "sample_data": null,
    "themes": null,
    "menus": {},
    "submenus": null,
    "keybindings": null,
    "configuration": []
  },
  "package_metadata": {
    "metadata_version": "2.1",
    "name": "napari-tomocube-data-viewer",
    "version": "2024.4",
    "dynamic": null,
    "platform": null,
    "supported_platform": null,
    "summary": "\"A plugin to visualize three-dimensional data from Tomocube's microscopy\"",
    "description": "# napari-tomocube-data-viewer\n\n[![License MIT](https://img.shields.io/badge/License-MIT-yellow.svg)](https://github.com/ehgus/napari-tomocube-data-viewer/raw/main/LICENSE)\n[![PyPI](https://img.shields.io/pypi/v/napari-tomocube-data-viewer.svg?color=green)](https://pypi.org/project/napari-tomocube-data-viewer)\n[![napari hub](https://img.shields.io/endpoint?url=https://api.napari-hub.org/shields/napari-tomocube-data-viewer)](https://napari-hub.org/plugins/napari-tomocube-data-viewer)\n\nA plugin to visualize three-dimensional data from [Tomocube](https://www.tomocube.com/)'s holotomography\n\n----------------------------------\n\nThis [napari] plugin was generated with [Cookiecutter] using [@napari]'s [cookiecutter-napari-plugin] template.\n\n<!--\nDon't miss the full getting started guide to set up your new package:\nhttps://github.com/napari/cookiecutter-napari-plugin#getting-started\n\nand review the napari docs for plugin developers:\nhttps://napari.org/stable/plugins/index.html\n-->\n\n## Installation\n\nYou can install `napari-tomocube-data-viewer` via [pip] or [conda]:\n\n    pip install napari-tomocube-data-viewer\n    conda install napari-tomocube-data-viewer\n\n## Contributing\n\nContributions are very welcome. Tests can be run with [tox], please ensure\nthe coverage at least stays the same before you submit a pull request.\n\n## License\n\nDistributed under the terms of the [MIT] license,\n\"napari-tomocube-data-viewer\" is free and open source software\n\n## Issues\n\nIf you encounter any problems, please [file an issue] along with a detailed description.\n\n[napari]: https://github.com/napari/napari\n[Cookiecutter]: https://github.com/audreyr/cookiecutter\n[@napari]: https://github.com/napari\n[MIT]: http://opensource.org/licenses/MIT\n[cookiecutter-napari-plugin]: https://github.com/napari/cookiecutter-napari-plugin\n[tox]: https://tox.readthedocs.io/en/latest/\n[pip]: https://pypi.org/project/pip/\n[conda]: https://docs.anaconda.com/free/miniconda/index.html\n[file an issue]: https://github.com/ehgus/napari-tomocube-data-viewer/issues\n",
    "description_content_type": "text/markdown",
    "keywords": null,
    "home_page": "https://github.com/ehgus/napari-tomocube-data-viewer",
    "download_url": null,
    "author": "Dohyeon Lee",
    "author_email": "dleh428@kaist.ac.kr",
    "maintainer": null,
    "maintainer_email": null,
    "license": "MIT",
    "classifier": [
      "Development Status :: 2 - Pre-Alpha",
      "Framework :: napari",
      "Intended Audience :: Developers",
      "License :: OSI Approved :: MIT License",
      "Operating System :: OS Independent",
      "Programming Language :: Python",
      "Programming Language :: Python :: 3",
      "Programming Language :: Python :: 3 :: Only",
      "Programming Language :: Python :: 3.8",
      "Programming Language :: Python :: 3.9",
      "Programming Language :: Python :: 3.10",
      "Topic :: Scientific/Engineering :: Image Processing"
    ],
    "requires_dist": [
      "numpy",
      "TCFile",
      "tox ; extra == 'testing'",
      "pytest ; extra == 'testing'",
      "pytest-cov ; extra == 'testing'"
    ],
    "requires_python": ">=3.8",
    "requires_external": null,
    "project_url": [
      "Bug Tracker, https://github.com/ehgus/napari-tomocube-data-viewer/issues",
      "Documentation, https://github.com/ehgus/napari-tomocube-data-viewer #README.md",
      "Source Code, https://github.com/ehgus/napari-tomocube-data-viewer",
      "User Support, https://github.com/ehgus/napari-tomocube-data-viewer/issues"
    ],
    "provides_extra": [
      "testing"
    ],
    "provides_dist": null,
    "obsoletes_dist": null
  },
  "npe1_shim": false
}