{"*": ["acquifer-napari", "imaxt-multiscale-plugin", "napari-amdtrk", "napari-apr-viewer", "napari-bil-data-viewer", "napari-bioformats", "napari-ccp4map", "napari-compressed-labels-io", "napari-compressed-labels-io", "napari-data-preview", "napari-deeplabcut", "napari-dvid", "napari-dzi-zarr", "napari-em-reader", "napari-hdf5-labels-io", "napari-hierarchical", "napari-hippo", "napari-imaris-loader", "napari-itk-io", "napari-lazy-openslide", "napari-medical-image-formats", "napari-mrcfile-handler", "napari-ndtiffs", "napari-nikon-nd2", "napari-pdf-reader", "napari-spacetx-explorer", "napari-spatial-omics", "napari-toothfairy-annotator", "napari-tracks-reader", "napari_video", "vessel-express-napari", "waver"], "*.1sc": ["napari-aicsimageio", "napari-bfio"], "*.2fl": ["napari-aicsimageio", "napari-bfio"], "*.3ds": ["napari-pymeshlab"], "*.3fr": ["napari-aicsimageio"], "*.CUB": ["napari-rioxarray"], "*.FITS": ["napari-pdr-reader", "napari-rioxarray"], "*.IMG": ["napari-pdr-reader", "napari-rioxarray"], "*.LBL": ["napari-pdr-reader", "napari-rioxarray"], "*.PTU": ["napari-flim-phasor-plotter"], "*.SDT": ["napari-flim-phasor-plotter"], "*.TCF": ["napari-tomocube-data-viewer"], "*.TIF": ["napari-deepfinder", "napari-rioxarray"], "*.TIFF": ["napari-rioxarray"], "*.acff": ["napari-aicsimageio", "napari-bfio"], "*.acqp": ["napari-aicsimageio"], "*.afi": ["napari-aicsimageio", "napari-bfio"], "*.afm": ["napari-aicsimageio", "napari-bfio"], "*.aim": ["napari-aicsimageio", "napari-bfio"], "*.al3d": ["napari-aicsimageio", "napari-bfio"], "*.ali": ["napari-aicsimageio", "napari-bfio", "napari-mrcfile-reader"], "*.am": ["napari-aicsimageio", "napari-bfio"], "*.amiramesh": ["napari-aicsimageio", "napari-bfio"], "*.ano": ["napari-aicsimageio"], "*.apl": ["napari-aicsimageio", "napari-bfio"], "*.apts": ["napari-pymeshlab"], "*.arf": ["napari-aicsimageio", "napari-bfio"], "*.array-like": ["napari-aicsimageio"], "*.arw": ["napari-aicsimageio"], "*.asc": ["napari-pymeshlab"], "*.avi": ["napari-aicsimageio", "napari-bfio", "napari-deeplabcut", "napari-video-cvdask"], "*.avs": ["napari-meshio"], "*.bay": ["napari-aicsimageio"], "*.bdf": ["napari-meshio"], "*.bif": ["napari-aicsimageio", "napari-bfio", "napari-wsi"], "*.bin": ["napari-aicsimageio", "napari-bfio"], "*.bip": ["napari-aicsimageio", "napari-bfio"], "*.bmp": ["napari-aicsimageio", "napari-bfio", "napari-hippo"], "*.bmq": ["napari-aicsimageio"], "*.box": ["blik", "napari-boxmanager"], "*.bre": ["napari-pymeshlab"], "*.bsdf": ["napari-aicsimageio"], "*.btf": ["napari-bfio"], "*.bufr": ["napari-aicsimageio"], "*.bw": ["napari-aicsimageio"], "*.bwp": ["napari-brainways"], "*.bz2": ["PartSeg"], "*.c01": ["napari-aicsimageio", "napari-bfio"], "*.cap": ["napari-aicsimageio"], "*.cat": ["napari-aicsimageio"], "*.cbox": ["blik", "napari-boxmanager"], "*.cfg": ["napari-aicsimageio", "napari-bfio"], "*.cgns": ["napari-meshio"], "*.ch5": ["napari-aicsimageio", "napari-bfio"], "*.cif": ["napari-aicsimageio", "napari-bfio", "napari-molecule-reader"], "*.cine": ["napari-aicsimageio"], "*.coords": ["napari-boxmanager"], "*.cr2": ["napari-aicsimageio", "napari-bfio"], "*.crw": ["napari-aicsimageio", "napari-bfio"], "*.cs": ["napari-boxmanager"], "*.cs1": ["napari-aicsimageio"], "*.csv": ["anchor-droplet-chip", "in-silico-fate-mapping", "napari-aicsimageio", "napari-bbox", "napari-bee-annotator", "napari-cell-centroid-annotator", "napari-gemspa", "napari-griottes", "napari-spotiflow", "napari-spreadsheet", "platetrack"], "*.ct": ["napari-aicsimageio"], "*.ct.img": ["napari-aicsimageio"], "*.ctm": ["napari-pymeshlab"], "*.cub": ["napari-rioxarray"], "*.cur": ["napari-aicsimageio"], "*.cut": ["napari-aicsimageio"], "*.cxd": ["napari-aicsimageio", "napari-bfio"], "*.czi": ["napari-aicsimageio", "napari-czifile2", "napari-sairyscan", "organelle-segmenter-plugin", "PartSeg", "PartSeg"], "*.dae": ["napari-pymeshlab"], "*.dat": ["napari-aicsimageio", "napari-bfio", "napari-hippo", "napari-meshio", "napari-spreadsheet"], "*.dato": ["napari-meshio"], "*.dato.gz": ["napari-meshio"], "*.db": ["napari-aicsimageio", "napari-bfio"], "*.dc2": ["napari-aicsimageio"], "*.dcm": ["mousechd-napari", "napari-aicsimageio", "napari-bfio", "napari-nibabel"], "*.dcr": ["napari-aicsimageio"], "*.dcx": ["napari-aicsimageio"], "*.dds": ["napari-aicsimageio"], "*.df3": ["napari-aicsimageio"], "*.dib": ["napari-bfio"], "*.dicom": ["napari-aicsimageio", "napari-bfio"], "*.dm2": ["napari-aicsimageio", "napari-bfio"], "*.dm3": ["napari-aicsimageio", "napari-bfio"], "*.dm4": ["napari-bfio"], "*.dng": ["napari-aicsimageio"], "*.drf": ["napari-aicsimageio"], "*.dsc": ["napari-aicsimageio"], "*.dti": ["napari-aicsimageio", "napari-bfio"], "*.dv": ["napari-aicsimageio", "napari-bfio", "napari-dv"], "*.e": ["napari-meshio"], "*.e57": ["napari-pymeshlab"], "*.ecw": ["napari-aicsimageio"], "*.ele": ["napari-meshio"], "*.em": ["blik"], "*.emd": ["napari-EMD"], "*.emf": ["napari-aicsimageio"], "*.eps": ["napari-aicsimageio", "napari-bfio"], "*.epsi": ["napari-aicsimageio", "napari-bfio"], "*.erf": ["napari-aicsimageio"], "*.es": ["napari-pymeshlab"], "*.exo": ["napari-meshio"], "*.exp": ["napari-aicsimageio", "napari-bfio"], "*.exr": ["napari-aicsimageio"], "*.f3grid": ["napari-meshio"], "*.fake": ["napari-aicsimageio"], "*.fbx": ["napari-pymeshlab"], "*.fdf": ["napari-aicsimageio", "napari-bfio"], "*.fem": ["napari-meshio"], "*.fff": ["napari-aicsimageio", "napari-bfio"], "*.ffr": ["napari-aicsimageio", "napari-bfio"], "*.fid": ["napari-aicsimageio"], "*.fit": ["napari-aicsimageio"], "*.fits": ["napari-aicsimageio", "napari-bfio", "napari-pdr-reader", "napari-rioxarray"], "*.flc": ["napari-aicsimageio"], "*.flex": ["napari-aicsimageio", "napari-bfio"], "*.fli": ["napari-aicsimageio", "napari-bfio"], "*.fpx": ["napari-aicsimageio"], "*.frm": ["napari-aicsimageio", "napari-bfio"], "*.ftc": ["napari-aicsimageio"], "*.fts": ["napari-aicsimageio"], "*.ftu": ["napari-aicsimageio"], "*.fz": ["napari-aicsimageio"], "*.fzy": ["napari-demo"], "*.fzzy": ["napari-demo"], "*.g3": ["napari-aicsimageio"], "*.gbr": ["napari-aicsimageio"], "*.gdcm": ["napari-aicsimageio"], "*.gel": ["napari-aicsimageio", "napari-bfio"], "*.geojson": ["napari-geojson"], "*.gif": ["napari-aicsimageio", "napari-bfio"], "*.gii": ["napari-nibabel"], "*.gipl": ["napari-aicsimageio"], "*.glb": ["napari-pymeshlab"], "*.gltf": ["napari-pymeshlab"], "*.grey": ["napari-aicsimageio", "napari-bfio"], "*.grib": ["napari-aicsimageio"], "*.griottes": ["napari-griottes"], "*.gz": ["PartSeg"], "*.h5": ["btrack", "napari-aicsimageio", "napari-bfio", "napari-deepfinder", "napari-deeplabcut", "napari-h5", "napari-ISM", "napari-lattice", "napari-melt-pool-tracker"], "*.h5m": ["napari-meshio"], "*.hdf": ["blik", "btrack", "napari-aicsimageio", "napari-bfio"], "*.hdf5": ["btrack", "napari-aicsimageio"], "*.hdp": ["napari-aicsimageio"], "*.hdr": ["napari-aicsimageio", "napari-bfio", "napari-hippo", "napari-nibabel"], "*.hed": ["napari-aicsimageio", "napari-bfio"], "*.his": ["napari-aicsimageio", "napari-bfio"], "*.htd": ["napari-aicsimageio", "napari-bfio"], "*.htm": ["napari-aicsimageio"], "*.html": ["napari-aicsimageio"], "*.hx": ["napari-aicsimageio", "napari-bfio"], "*.i2i": ["napari-aicsimageio", "napari-bfio"], "*.ia": ["napari-aicsimageio"], "*.icns": ["napari-aicsimageio"], "*.ico": ["napari-aicsimageio"], "*.ics": ["napari-aicsimageio", "napari-bfio"], "*.ids": ["napari-aicsimageio", "napari-bfio"], "*.iff": ["napari-aicsimageio"], "*.iim": ["napari-aicsimageio"], "*.iiq": ["napari-aicsimageio"], "*.im": ["napari-aicsimageio"], "*.im3": ["napari-aicsimageio", "napari-bfio"], "*.img": ["napari-aicsimageio", "napari-bfio", "napari-bfio", "napari-pdr-reader", "napari-rioxarray"], "*.imggz": ["napari-aicsimageio"], "*.ims": ["napari-aicsimageio", "napari-bfio"], "*.imzML": ["MSI-Explorer"], "*.inf": ["napari-aicsimageio"], "*.inp": ["napari-meshio"], "*.inr": ["napari-aicsimageio", "napari-bfio"], "*.ipl": ["napari-aicsimageio", "napari-bfio"], "*.ipm": ["napari-aicsimageio", "napari-bfio"], "*.ipw": ["napari-aicsimageio", "napari-bfio"], "*.j2c": ["napari-aicsimageio"], "*.j2k": ["napari-aicsimageio", "napari-bfio"], "*.jfif": ["napari-aicsimageio"], "*.jif": ["napari-aicsimageio"], "*.jng": ["napari-aicsimageio"], "*.jp2": ["napari-aicsimageio", "napari-bfio"], "*.jpc": ["napari-aicsimageio"], "*.jpe": ["napari-aicsimageio"], "*.jpeg": ["napari-aicsimageio", "napari-bfio", "napari-deeplabcut", "napari-hippo"], "*.jpf": ["napari-aicsimageio", "napari-bfio"], "*.jpg": ["napari-aicsimageio", "napari-bfio", "napari-deeplabcut", "napari-hippo"], "*.jpk": ["napari-aicsimageio", "napari-bfio"], "*.jpx": ["napari-aicsimageio", "napari-bfio"], "*.json": ["napari-griottes", "napari-organoid-counter", "napari-pram", "yt-napari"], "*.jxr": ["napari-aicsimageio"], "*.k25": ["napari-aicsimageio"], "*.kc2": ["napari-aicsimageio"], "*.kdc": ["napari-aicsimageio"], "*.klb": ["napari-aicsimageio", "napari-bfio"], "*.koa": ["napari-aicsimageio"], "*.l2d": ["napari-aicsimageio", "napari-bfio"], "*.labels": ["napari-aicsimageio", "napari-bfio"], "*.lbl": ["napari-pdr-reader", "napari-rioxarray"], "*.lbl.json": ["napari-labeling"], "*.lbm": ["napari-aicsimageio"], "*.lei": ["napari-aicsimageio", "napari-bfio"], "*.lfp": ["napari-aicsimageio"], "*.lfr": ["napari-aicsimageio"], "*.lif": ["napari-aicsimageio", "napari-bfio"], "*.liff": ["napari-aicsimageio", "napari-bfio"], "*.lim": ["napari-aicsimageio", "napari-bfio"], "*.lms": ["napari-aicsimageio", "napari-bfio"], "*.lof": ["napari-bfio"], "*.lsm": ["napari-aicsimageio", "napari-bfio", "PartSeg", "PartSeg"], "*.map": ["blik", "napari-bfio", "napari-deepfinder", "napari-mrcfile-reader"], "*.mat": ["napari-mat-file-reader"], "*.mcd": ["napari-imc", "napari-steinpose"], "*.mdb": ["napari-aicsimageio", "napari-bfio"], "*.mdc": ["napari-aicsimageio"], "*.mdpa": ["napari-meshio"], "*.mea": ["napari-bfio"], "*.med": ["napari-meshio"], "*.mef": ["napari-aicsimageio"], "*.mesh": ["napari-meshio"], "*.meshb": ["napari-meshio"], "*.mgh": ["napari-aicsimageio"], "*.mha": ["napari-aicsimageio"], "*.mhd": ["napari-aicsimageio"], "*.mic": ["napari-aicsimageio"], "*.mkv": ["napari-aicsimageio"], "*.mnc": ["napari-aicsimageio", "napari-bfio"], "*.mnc2": ["napari-aicsimageio"], "*.mng": ["napari-aicsimageio", "napari-bfio"], "*.mod": ["napari-aicsimageio", "napari-bfio"], "*.mos": ["napari-aicsimageio"], "*.mov": ["napari-aicsimageio", "napari-bfio", "napari-deeplabcut", "napari-video-cvdask"], "*.mp4": ["napari-aicsimageio", "napari-deeplabcut", "napari-video-cvdask"], "*.mpeg": ["napari-aicsimageio"], "*.mpg": ["napari-aicsimageio"], "*.mpo": ["napari-aicsimageio"], "*.mrc": ["blik", "napari-aicsimageio", "napari-bfio", "napari-boxmanager", "napari-deepfinder", "napari-dv", "napari-mrcfile-reader"], "*.mrci": ["napari-boxmanager"], "*.mrcs": ["blik", "napari-bfio", "napari-boxmanager", "napari-mrcfile-reader"], "*.mri": ["napari-aicsimageio"], "*.mrw": ["napari-aicsimageio", "napari-bfio"], "*.msh": ["napari-meshio", "napari-meshio"], "*.msp": ["napari-aicsimageio"], "*.msr": ["napari-aicsimageio", "napari-bfio"], "*.mtb": ["napari-aicsimageio", "napari-bfio"], "*.mvd2": ["napari-aicsimageio", "napari-bfio"], "*.mzarr": ["napari-mzarr"], "*.mzz": ["napari-mzarr"], "*.n3d": ["napari-threedee"], "*.naf": ["napari-aicsimageio", "napari-bfio"], "*.nas": ["napari-meshio"], "*.nd": ["napari-aicsimageio", "napari-bfio"], "*.nd2": ["anchor-droplet-chip", "napari-aicsimageio", "napari-bfio", "napari-segment"], "*.ndjson": ["napari-cryoet-data-portal"], "*.ndpi": ["napari-aicsimageio", "napari-bfio", "napari-wsi"], "*.ndpis": ["napari-aicsimageio", "napari-bfio"], "*.nef": ["napari-aicsimageio", "napari-bfio"], "*.nhdr": ["napari-aicsimageio", "napari-bfio"], "*.nia": ["napari-aicsimageio"], "*.nii": ["napari-aicsimageio", "napari-bfio", "napari-nibabel", "napari-nifti"], "*.nii.gz": ["mousechd-napari", "napari-aicsimageio", "napari-bfio", "napari-nibabel", "napari-nifti"], "*.niigz": ["napari-aicsimageio"], "*.node": ["napari-meshio"], "*.npy": ["anchor-droplet-chip", "avidaq", "napari-apple", "napari-biomag-annotator", "napari-blossom", "napari-bud-cell-segmenter", "napari-buds", "napari-caphid", "napari-cell-centroid-annotator", "napari-cookiecut", "napari-curviewer", "napari-griottes", "napari-indices", "napari-ISM", "napari-LF", "napari-parallel", "napari-pixel-correction", "napari-potential-field-navigation", "napari-segment", "napari-sketchpose", "napari-superres", "napari-svetlana", "napari-workshop-plugin"], "*.npz": ["napari-aicsimageio"], "*.nrrd": ["mousechd-napari", "napari-aicsimageio", "napari-bfio"], "*.nrw": ["napari-aicsimageio"], "*.obf": ["napari-aicsimageio", "napari-bfio"], "*.obj": ["napari-meshio", "napari-obj", "napari-pymeshlab", "napari-shape-odyssey", "napari-stl-exporter", "surforama"], "*.obsep": ["napari-bfio", "PartSeg"], "*.ods": ["napari-deepfinder"], "*.off": ["napari-meshio", "napari-pymeshlab", "napari-shape-odyssey"], "*.oib": ["napari-aicsimageio", "napari-bfio", "PartSeg", "PartSeg"], "*.oif": ["napari-aicsimageio", "napari-bfio", "PartSeg", "PartSeg"], "*.oir": ["napari-aicsimageio", "napari-bfio"], "*.ome": ["napari-aicsimageio"], "*.ome.tif": ["napari-aicsimageio", "napari-bfio"], "*.ome.tiff": ["napari-aicsimageio", "napari-bfio"], "*.ome.zarr": ["iterseg", "napari-bfio"], "*.omp2info": ["napari-bfio"], "*.orf": ["napari-aicsimageio"], "*.par": ["napari-aicsimageio", "napari-bfio", "napari-nibabel"], "*.parquet": ["platetrack"], "*.pbm": ["napari-aicsimageio", "napari-bfio"], "*.pcd": ["napari-aicsimageio"], "*.pcoraw": ["napari-aicsimageio", "napari-bfio"], "*.pct": ["napari-aicsimageio"], "*.pcx": ["napari-aicsimageio", "napari-bfio"], "*.pdb": ["napari-molecule-reader", "napari-pymeshlab"], "*.pds": ["napari-bfio"], "*.pef": ["napari-aicsimageio"], "*.pfm": ["napari-aicsimageio"], "*.pgm": ["napari-aicsimageio", "napari-bfio"], "*.pic": ["napari-aicsimageio", "napari-bfio"], "*.picks": ["blik"], "*.pict": ["napari-aicsimageio", "napari-bfio"], "*.ply": ["napari-meshio", "napari-pymeshlab", "napari-shape-odyssey", "napari-stl-exporter"], "*.png": ["napari-aicsimageio", "napari-bfio", "napari-deeplabcut", "napari-hippo", "napari-pram"], "*.pnl": ["napari-aicsimageio", "napari-bfio"], "*.post": ["napari-meshio"], "*.post.gz": ["napari-meshio"], "*.ppm": ["napari-aicsimageio", "napari-bfio"], "*.pr3": ["napari-aicsimageio", "napari-bfio"], "*.preali": ["napari-mrcfile-reader"], "*.ps": ["napari-aicsimageio", "napari-bfio"], "*.psd": ["napari-aicsimageio", "napari-bfio"], "*.ptu": ["napari-flim-phasor-plotter"], "*.ptx": ["napari-aicsimageio", "napari-pymeshlab"], "*.pxn": ["napari-aicsimageio"], "*.pxr": ["napari-aicsimageio"], "*.qobj": ["napari-pymeshlab"], "*.qptiff": ["napari-aicsimageio", "napari-bfio", "napari-wsi"], "*.qtk": ["napari-aicsimageio"], "*.r3d": ["napari-aicsimageio", "napari-bfio"], "*.raf": ["napari-aicsimageio"], "*.ras": ["napari-aicsimageio"], "*.raw": ["napari-aicsimageio", "napari-bfio"], "*.rcpnl": ["napari-aicsimageio", "napari-bfio"], "*.rdc": ["napari-aicsimageio"], "*.rec": ["blik", "napari-aicsimageio", "napari-bfio", "napari-boxmanager", "napari-deepfinder", "napari-mrcfile-reader"], "*.res": ["napari-bfio"], "*.rgb": ["napari-aicsimageio"], "*.rgba": ["napari-aicsimageio"], "*.rw2": ["napari-aicsimageio"], "*.rwl": ["napari-aicsimageio"], "*.rwz": ["napari-aicsimageio"], "*.scan": ["napari-aicsimageio"], "*.scn": ["napari-aicsimageio", "napari-bfio", "napari-wsi"], "*.sdt": ["napari-aicsimageio", "napari-bfio", "napari-flim-phasor-plotter"], "*.seg": ["PartSeg"], "*.seq": ["napari-aicsimageio", "napari-bfio"], "*.sif": ["napari-aicsimageio", "napari-bfio", "napari-sif-reader"], "*.sld": ["napari-aicsimageio", "napari-bfio"], "*.sldy": ["napari-bfio"], "*.sm2": ["napari-aicsimageio", "napari-bfio"], "*.sm3": ["napari-aicsimageio", "napari-bfio"], "*.spc": ["napari-aicsimageio", "napari-bfio"], "*.spe": ["napari-aicsimageio", "napari-bfio"], "*.spi": ["napari-aicsimageio", "napari-bfio"], "*.splineit": ["napari-splineit"], "*.sr2": ["napari-aicsimageio"], "*.srf": ["napari-aicsimageio"], "*.srw": ["napari-aicsimageio"], "*.st": ["blik", "napari-aicsimageio", "napari-bfio", "napari-boxmanager", "napari-mrcfile-reader"], "*.star": ["blik", "napari-boxmanager"], "*.sti": ["napari-aicsimageio"], "*.stk": ["napari-aicsimageio", "napari-bfio"], "*.stl": ["napari-meshio", "napari-pymeshlab", "napari-shape-odyssey", "napari-stl-exporter"], "*.stp": ["napari-aicsimageio", "napari-bfio"], "*.su2": ["napari-meshio"], "*.surf": ["blik"], "*.svs": ["napari-aicsimageio", "napari-bfio", "napari-wsi"], "*.swf": ["napari-aicsimageio"], "*.sxm": ["napari-aicsimageio", "napari-bfio"], "*.targa": ["napari-aicsimageio"], "*.tbl": ["blik"], "*.tbz2": ["PartSeg"], "*.tdb": ["napari-tiledb-bioimg"], "*.temb": ["napari-boxmanager"], "*.tf2": ["napari-bfio"], "*.tf8": ["napari-bfio"], "*.tfr": ["napari-aicsimageio", "napari-bfio"], "*.tga": ["napari-aicsimageio", "napari-bfio"], "*.tgz": ["PartSeg", "PartSeg"], "*.thm": ["napari-aicsimageio"], "*.tif": ["anchor-droplet-chip", "brainglobe-napari-io", "epitools", "Large-Image-Viewer", "napari-aicsimageio", "napari-bfio", "napari-bfio", "napari-boxmanager", "napari-cell-centroid-annotator", "napari-clemreg", "napari-deepfinder", "napari-flim-phasor-plotter", "napari-griottes", "napari-microtubule-analyzer", "napari-rioxarray", "napari-segment", "napari-tiff", "napari-wsi", "organelle-segmenter-plugin", "PartSeg", "PartSeg", "recOrder-napari"], "*.tiff": ["brainglobe-napari-io", "brainglobe-napari-io", "epitools", "Large-Image-Viewer", "napari-aicsimageio", "napari-bfio", "napari-bfio", "napari-boxmanager", "napari-cell-centroid-annotator", "napari-clemreg", "napari-griottes", "napari-microtubule-analyzer", "napari-rioxarray", "napari-tiff", "napari-wsi", "organelle-segmenter-plugin", "PartSeg", "PartSeg"], "*.tiledb": ["napari-tiledb-bioimg"], "*.tim": ["napari-aicsimageio"], "*.tloc": ["napari-boxmanager"], "*.tmap": ["napari-boxmanager"], "*.tnb": ["napari-aicsimageio", "napari-bfio"], "*.top": ["napari-aicsimageio", "napari-bfio"], "*.tsv": ["napari-gemspa"], "*.txt": ["napari-aicsimageio", "napari-bfio", "napari-gemspa", "napari-imc", "napari-spreadsheet"], "*.ugrid": ["napari-meshio"], "*.v": ["napari-aicsimageio", "napari-bfio"], "*.vff": ["napari-aicsimageio", "napari-bfio"], "*.vmi": ["napari-pymeshlab"], "*.vms": ["napari-aicsimageio", "napari-bfio"], "*.vol": ["napari-meshio"], "*.vol.gz": ["napari-meshio"], "*.vrt": ["napari-rioxarray"], "*.vsi": ["napari-aicsimageio", "napari-bfio"], "*.vtk": ["napari-aicsimageio", "napari-meshio", "napari-shape-odyssey"], "*.vtp": ["napari-shape-odyssey"], "*.vtu": ["napari-meshio"], "*.vws": ["napari-aicsimageio", "napari-bfio"], "*.wap": ["napari-aicsimageio"], "*.wat": ["napari-aicsimageio", "napari-bfio"], "*.wav": ["napari-aicsimageio"], "*.wbm": ["napari-aicsimageio"], "*.wbmp": ["napari-aicsimageio"], "*.wdp": ["napari-aicsimageio"], "*.webp": ["napari-aicsimageio"], "*.wkt": ["napari-meshio"], "*.wlz": ["napari-aicsimageio"], "*.wmf": ["napari-aicsimageio"], "*.wmv": ["napari-aicsimageio"], "*.wpi": ["napari-aicsimageio", "napari-bfio"], "*.wrl": ["napari-pymeshlab"], "*.x3d": ["napari-pymeshlab"], "*.xbm": ["napari-aicsimageio"], "*.xdce": ["napari-aicsimageio", "napari-bfio"], "*.xdmf": ["napari-meshio"], "*.xlef": ["napari-bfio"], "*.xls": ["napari-deepfinder"], "*.xlsx": ["napari-deepfinder", "napari-spreadsheet"], "*.xmf": ["napari-meshio"], "*.xml": ["brainglobe-napari-io", "napari-aicsimageio", "napari-deepfinder", "napari-imagej", "napari-meshio"], "*.xpm": ["napari-aicsimageio"], "*.xqd": ["napari-aicsimageio", "napari-bfio"], "*.xqf": ["napari-aicsimageio", "napari-bfio"], "*.xv": ["napari-aicsimageio", "napari-bfio"], "*.xys": ["napari-aicsimageio", "napari-bfio"], "*.xyz": ["organelle-segmenter-plugin"], "*.yaml": ["napari-deeplabcut"], "*.ysc": ["spots-in-yeasts"], "*.zarr": ["anchor-droplet-chip", "napari-cryoet-data-portal", "napari-dexp", "napari-flim-phasor-plotter", "napari-ome-zarr", "napari-spatialdata", "recOrder-napari", "zarpaint"], "*.zarr*": ["napari-ome-zarr"], "*.zarr.zip": ["napari-dexp"], "*.zfp": ["napari-aicsimageio", "napari-bfio"], "*.zfr": ["napari-aicsimageio", "napari-bfio"], "*.zip": ["napari-aicsimageio", "napari-argos-archive-reader", "napari-tiff"], "*.zpo": ["napari-aicsimageio"], "*.zvi": ["napari-aicsimageio", "napari-bfio"], ".x3dv": ["napari-pymeshlab"], "<EDIT_ME>": ["napari-annotatorj"], "http://*": ["napari-demo"], "https://*": ["napari-demo"], "omero://*": ["napari-omero"], "s3://*": ["napari-tiledb-bioimg"], "tiledb://*": ["napari-tiledb-bioimg"]}