{
  "url": "https://github.com/sommerc/napari-correct-drift",
  "activity": {
    "default_branch": "main",
    "open_issues": 0,
    "pull_requests": 0,
    "forks": 1,
    "stars": 2,
    "watchers": 3,
    "is_archived": false,
    "open_runtime_vulnerability_alerts": 0,
    "last_commit": {
      "date": "2023-11-06T12:59:59Z",
      "message": "More doc 5/n",
      "author_name": "Christoph Sommer",
      "author_login": "sommerc"
    }
  },
  "coverage": {
    "hits": 719,
    "lines": 867,
    "ratio": 82.92964,
    "commit": "331a4c9f1a013bf74423941ea865d6e2dd7446e8",
    "date": "2023-11-06T12:59:59",
    "branch": "main"
  }
}