{
  "url": "https://github.com/mertesdorfj/napari-persistent-homology",
  "activity": {
    "default_branch": "main",
    "open_issues": 0,
    "pull_requests": 1,
    "forks": 0,
    "stars": 0,
    "watchers": 0,
    "is_archived": false,
    "open_runtime_vulnerability_alerts": 0,
    "last_commit": {
      "date": "2026-07-10T13:57:11Z",
      "message": "Add data-prep helper notebook",
      "author_name": "mertesdorfj",
      "author_login": "mertesdorfj"
    }
  },
  "coverage": {
    "hits": 692,
    "lines": 859,
    "ratio": 80.55,
    "commit": "05132334801896862ae19ee7e08d584e3acdc3bd",
    "date": "2026-07-10T13:57:11Z",
    "branch": "main"
  }
}