{
  "url": "https://github.com/ome/napari-ome-zarr",
  "activity": {
    "default_branch": "main",
    "open_issues": 17,
    "pull_requests": 4,
    "forks": 18,
    "stars": 15,
    "watchers": 10,
    "is_archived": false,
    "open_runtime_vulnerability_alerts": 0,
    "last_commit": {
      "date": "2023-04-11T07:14:48Z",
      "message": "Merge pull request #88 from ome/pre-commit-ci-update-config",
      "author_name": "jean-marie burel",
      "author_login": "jburel"
    }
  },
  "coverage": null
}