{
  "url": "https://github.com/fractal-napari-plugins-collection/napari-feature-classifier",
  "activity": {
    "default_branch": "main",
    "open_issues": 15,
    "pull_requests": 1,
    "forks": 5,
    "stars": 18,
    "watchers": 6,
    "is_archived": false,
    "open_runtime_vulnerability_alerts": 0,
    "last_commit": {
      "date": "2023-09-20T16:50:26Z",
      "message": "Merge pull request #37 from fdsteffen/main",
      "author_name": "Joel L\u00fcthi",
      "author_login": "jluethi"
    }
  },
  "coverage": {
    "hits": 649,
    "lines": 764,
    "ratio": 84.94764,
    "commit": "1d76ab6d77d0f2b828a52041a6c4ba5e3007c9e6",
    "date": "2023-09-20T16:50:26",
    "branch": "main"
  }
}